airflow_dag_dependencies/__init__.py
airflow_dag_dependencies/plugins/__init__.py
airflow_dag_dependencies/plugins/dags_dependencies_plugin.py
airflow_dag_dependencies-0.1.0.dist-info/LICENSE
airflow_dag_dependencies-0.1.0.dist-info/METADATA
airflow_dag_dependencies-0.1.0.dist-info/WHEEL
airflow_dag_dependencies-0.1.0.dist-info/entry_points.txt
airflow_dag_dependencies-0.1.0.dist-info/RECORD
