Metadata-Version: 2.3
Name: airflow-dag-dependencies
Version: 0.1.0
Summary: An Apache Airflow plugin that provides interactive visualization of DAG dependencies, datasets, and trigger relationships. Enhance your workflow monitoring and planning with intuitive D3.js-powered graphs.
License: MIT
Author: Ponder
Requires-Python: >=3.12,<3.14
Classifier: License :: OSI Approved :: MIT License
Classifier: Programming Language :: Python :: 3
Classifier: Programming Language :: Python :: 3.12
Classifier: Programming Language :: Python :: 3.13
Requires-Dist: apache-airflow (>=3.1.0,<4.0.0)
Project-URL: homepage, https://github.com/ponderedw/airflow-dag-dependencies
